molsystem/__init__.py
molsystem/_version.py
molsystem/align.py
molsystem/atoms.py
molsystem/bonds.py
molsystem/cell.py
molsystem/cif.py
molsystem/cms_schema.py
molsystem/column.py
molsystem/configuration.py
molsystem/configuration_properties.py
molsystem/elements.py
molsystem/frozencolumn.py
molsystem/inchi.py
molsystem/molfile.py
molsystem/openbabel.py
molsystem/openeye.py
molsystem/pdb.py
molsystem/properties.py
molsystem/pubchem.py
molsystem/qcschema.py
molsystem/rdkit_.py
molsystem/smiles.py
molsystem/subset.py
molsystem/subsets.py
molsystem/symmetry.py
molsystem/system.py
molsystem/system_db.py
molsystem/system_properties.py
molsystem/table.py
molsystem/template.py
molsystem/templates.py
molsystem/topology.py
molsystem/data/standard_properties.csv
molsystem-2025.12.21.dist-info/licenses/AUTHORS.rst
molsystem-2025.12.21.dist-info/licenses/LICENSE
molsystem-2025.12.21.dist-info/METADATA
molsystem-2025.12.21.dist-info/WHEEL
molsystem-2025.12.21.dist-info/top_level.txt
molsystem-2025.12.21.dist-info/RECORD
